huaweicloudsdkkafka/__init__.py
huaweicloudsdkkafka/v2/__init__.py
huaweicloudsdkkafka/v2/kafka_async_client.py
huaweicloudsdkkafka/v2/kafka_client.py
huaweicloudsdkkafka/v2/model/__init__.py
huaweicloudsdkkafka/v2/model/access_policy_entity.py
huaweicloudsdkkafka/v2/model/access_policy_topic_entity.py
huaweicloudsdkkafka/v2/model/alter_auto_volume_expand_config.py
huaweicloudsdkkafka/v2/model/available_zones_resp.py
huaweicloudsdkkafka/v2/model/batch_create_or_delete_kafka_tag_request.py
huaweicloudsdkkafka/v2/model/batch_create_or_delete_kafka_tag_response.py
huaweicloudsdkkafka/v2/model/batch_create_or_delete_tag_req.py
huaweicloudsdkkafka/v2/model/batch_delete_group_req.py
huaweicloudsdkkafka/v2/model/batch_delete_group_request.py
huaweicloudsdkkafka/v2/model/batch_delete_group_resp_failed_groups.py
huaweicloudsdkkafka/v2/model/batch_delete_group_response.py
huaweicloudsdkkafka/v2/model/batch_delete_instance_topic_req.py
huaweicloudsdkkafka/v2/model/batch_delete_instance_topic_request.py
huaweicloudsdkkafka/v2/model/batch_delete_instance_topic_resp_topics.py
huaweicloudsdkkafka/v2/model/batch_delete_instance_topic_response.py
huaweicloudsdkkafka/v2/model/batch_delete_instance_users_req.py
huaweicloudsdkkafka/v2/model/batch_delete_instance_users_request.py
huaweicloudsdkkafka/v2/model/batch_delete_instance_users_response.py
huaweicloudsdkkafka/v2/model/batch_delete_message_diagnosis_reports_req.py
huaweicloudsdkkafka/v2/model/batch_delete_message_diagnosis_reports_request.py
huaweicloudsdkkafka/v2/model/batch_delete_message_diagnosis_reports_response.py
huaweicloudsdkkafka/v2/model/batch_delete_message_diagnosis_resp_results.py
huaweicloudsdkkafka/v2/model/batch_modift_group_description_req.py
huaweicloudsdkkafka/v2/model/batch_restart_or_delete_instance_req.py
huaweicloudsdkkafka/v2/model/batch_restart_or_delete_instance_resp_results.py
huaweicloudsdkkafka/v2/model/batch_restart_or_delete_instances_request.py
huaweicloudsdkkafka-3.1.184.dist-info/METADATA
huaweicloudsdkkafka-3.1.184.dist-info/WHEEL
huaweicloudsdkkafka-3.1.184.dist-info/licenses/LICENSE
huaweicloudsdkkafka-3.1.184.dist-info/RECORD
